linefolio/__init__.py
linefolio/_seaborn.py
linefolio/_version.py
linefolio/capacity.py
linefolio/deprecate.py
linefolio/examples/bayesian.ipynb
linefolio/examples/fama_french_benchmark.ipynb
linefolio/examples/full_tear_sheet_example.ipynb
linefolio/examples/pydata_stack-4-finance.jpg
linefolio/examples/pyfolio_talk_slides.ipynb
linefolio/examples/round_trip_tear_sheet_example.ipynb
linefolio/examples/sector_mappings_example.ipynb
linefolio/examples/single_stock_example.ipynb
linefolio/examples/slippage_example.ipynb
linefolio/examples/zipline_algo_example.ipynb
linefolio/interesting_periods.py
linefolio/ipycompat.py
linefolio/perf_attrib.py
linefolio/plotting.py
linefolio/pos.py
linefolio/quantrocket_moonshot.py
linefolio/quantrocket_utils.py
linefolio/quantrocket_zipline.py
linefolio/round_trips.py
linefolio/tears.py
linefolio/tests/__init__.py
linefolio/tests/matplotlibrc
linefolio/tests/test_capacity.py
linefolio/tests/test_data/__init__.py
linefolio/tests/test_data/factor_loadings.csv
linefolio/tests/test_data/factor_returns.csv
linefolio/tests/test_data/intercepts.csv
linefolio/tests/test_data/moonline-tearsheet.csv
linefolio/tests/test_data/positions.csv
linefolio/tests/test_data/residuals.csv
linefolio/tests/test_data/returns.csv
linefolio/tests/test_data/test_LMCAP.csv
linefolio/tests/test_data/test_LT_MOMENTUM.csv
linefolio/tests/test_data/test_MACDSignal.csv
linefolio/tests/test_data/test_VLTY.csv
linefolio/tests/test_data/test_caps.csv
linefolio/tests/test_data/test_gross_lev.csv.gz
linefolio/tests/test_data/test_pos.csv.gz
linefolio/tests/test_data/test_returns.csv.gz
linefolio/tests/test_data/test_sectors.csv
linefolio/tests/test_data/test_shares_held.csv
linefolio/tests/test_data/test_txn.csv.gz
linefolio/tests/test_data/test_volumes.csv
linefolio/tests/test_perf_attrib.py
linefolio/tests/test_pos.py
linefolio/tests/test_round_trips.py
linefolio/tests/test_tears.py
linefolio/tests/test_tears_moonline.py
linefolio/tests/test_timeseries.py
linefolio-1.8.0.dist-info/LICENSE
linefolio-1.8.0.dist-info/WHEEL
linefolio-1.8.0.dist-info/METADATA
linefolio-1.8.0.dist-info/RECORD
